{"dependencies":[{"name":"/Users/kennethchong/Documents/GitHub/typescript/package.json","includedInParent":true,"mtime":1605036142303}],"generated":{"js":"\"use strict\";\n\nObject.defineProperty(exports, \"__esModule\", { value: true });\nexports.Type2 = void 0;\nvar Job;\n(function (Job) {\n    Job[Job[\"WebDev\"] = 0] = \"WebDev\";\n    Job[Job[\"WebDesigner\"] = 1] = \"WebDesigner\";\n    Job[Job[\"PM\"] = 2] = \"PM\";\n})(Job || (Job = {}));\nexports.default = Job;\nvar Type2;\n(function (Type2) {\n    Type2[\"Video\"] = \"VIDEO\";\n    Type2[\"BlogPost\"] = \"BLOG_POST\";\n    Type2[\"Quiz\"] = \"QUIZ\";\n})(Type2 = exports.Type2 || (exports.Type2 = {}));","map":{"mappings":[{"generated":{"line":1,"column":0},"source":"src/interfaces.ts","original":{"line":1,"column":0}},{"name":"Object","generated":{"line":3,"column":0},"source":"src/interfaces.ts","original":{"line":2,"column":0}},{"name":"defineProperty","generated":{"line":3,"column":7},"source":"src/interfaces.ts","original":{"line":2,"column":7}},{"generated":{"line":3,"column":21},"source":"src/interfaces.ts","original":{"line":2,"column":0}},{"name":"exports","generated":{"line":3,"column":22},"source":"src/interfaces.ts","original":{"line":2,"column":22}},{"generated":{"line":3,"column":29},"source":"src/interfaces.ts","original":{"line":2,"column":0}},{"generated":{"line":3,"column":31},"source":"src/interfaces.ts","original":{"line":2,"column":31}},{"generated":{"line":3,"column":43},"source":"src/interfaces.ts","original":{"line":2,"column":0}},{"generated":{"line":3,"column":45},"source":"src/interfaces.ts","original":{"line":2,"column":45}},{"name":"value","generated":{"line":3,"column":47},"source":"src/interfaces.ts","original":{"line":2,"column":47}},{"generated":{"line":3,"column":54},"source":"src/interfaces.ts","original":{"line":2,"column":54}},{"generated":{"line":3,"column":58},"source":"src/interfaces.ts","original":{"line":2,"column":45}},{"generated":{"line":3,"column":60},"source":"src/interfaces.ts","original":{"line":2,"column":0}},{"name":"exports","generated":{"line":4,"column":0},"source":"src/interfaces.ts","original":{"line":3,"column":0}},{"name":"Type2","generated":{"line":4,"column":8},"source":"src/interfaces.ts","original":{"line":3,"column":8}},{"generated":{"line":4,"column":13},"source":"src/interfaces.ts","original":{"line":3,"column":0}},{"generated":{"line":4,"column":16},"source":"src/interfaces.ts","original":{"line":3,"column":16}},{"generated":{"line":4,"column":21},"source":"src/interfaces.ts","original":{"line":3,"column":21}},{"generated":{"line":4,"column":22},"source":"src/interfaces.ts","original":{"line":3,"column":0}},{"generated":{"line":5,"column":0},"source":"src/interfaces.ts","original":{"line":4,"column":0}},{"name":"Job","generated":{"line":5,"column":4},"source":"src/interfaces.ts","original":{"line":4,"column":4}},{"generated":{"line":5,"column":7},"source":"src/interfaces.ts","original":{"line":4,"column":0}},{"generated":{"line":6,"column":0},"source":"src/interfaces.ts","original":{"line":5,"column":0}},{"generated":{"line":6,"column":1},"source":"src/interfaces.ts","original":{"line":5,"column":1}},{"name":"Job","generated":{"line":6,"column":11},"source":"src/interfaces.ts","original":{"line":5,"column":11}},{"generated":{"line":6,"column":14},"source":"src/interfaces.ts","original":{"line":5,"column":1}},{"generated":{"line":6,"column":16},"source":"src/interfaces.ts","original":{"line":5,"column":16}},{"name":"Job","generated":{"line":7,"column":0},"source":"src/interfaces.ts","original":{"line":6,"column":4}},{"name":"Job","generated":{"line":7,"column":8},"source":"src/interfaces.ts","original":{"line":6,"column":8}},{"generated":{"line":7,"column":12},"source":"src/interfaces.ts","original":{"line":6,"column":12}},{"generated":{"line":7,"column":20},"source":"src/interfaces.ts","original":{"line":6,"column":8}},{"generated":{"line":7,"column":24},"source":"src/interfaces.ts","original":{"line":6,"column":24}},{"generated":{"line":7,"column":25},"source":"src/interfaces.ts","original":{"line":6,"column":4}},{"generated":{"line":7,"column":29},"source":"src/interfaces.ts","original":{"line":6,"column":29}},{"generated":{"line":7,"column":37},"source":"src/interfaces.ts","original":{"line":6,"column":4}},{"name":"Job","generated":{"line":8,"column":0},"source":"src/interfaces.ts","original":{"line":7,"column":4}},{"name":"Job","generated":{"line":8,"column":8},"source":"src/interfaces.ts","original":{"line":7,"column":8}},{"generated":{"line":8,"column":12},"source":"src/interfaces.ts","original":{"line":7,"column":12}},{"generated":{"line":8,"column":25},"source":"src/interfaces.ts","original":{"line":7,"column":8}},{"generated":{"line":8,"column":29},"source":"src/interfaces.ts","original":{"line":7,"column":29}},{"generated":{"line":8,"column":30},"source":"src/interfaces.ts","original":{"line":7,"column":4}},{"generated":{"line":8,"column":34},"source":"src/interfaces.ts","original":{"line":7,"column":34}},{"generated":{"line":8,"column":47},"source":"src/interfaces.ts","original":{"line":7,"column":4}},{"name":"Job","generated":{"line":9,"column":0},"source":"src/interfaces.ts","original":{"line":8,"column":4}},{"name":"Job","generated":{"line":9,"column":8},"source":"src/interfaces.ts","original":{"line":8,"column":8}},{"generated":{"line":9,"column":12},"source":"src/interfaces.ts","original":{"line":8,"column":12}},{"generated":{"line":9,"column":16},"source":"src/interfaces.ts","original":{"line":8,"column":8}},{"generated":{"line":9,"column":20},"source":"src/interfaces.ts","original":{"line":8,"column":20}},{"generated":{"line":9,"column":21},"source":"src/interfaces.ts","original":{"line":8,"column":4}},{"generated":{"line":9,"column":25},"source":"src/interfaces.ts","original":{"line":8,"column":25}},{"generated":{"line":9,"column":29},"source":"src/interfaces.ts","original":{"line":8,"column":4}},{"generated":{"line":10,"column":0},"source":"src/interfaces.ts","original":{"line":9,"column":1}},{"generated":{"line":10,"column":1},"source":"src/interfaces.ts","original":{"line":5,"column":0}},{"name":"Job","generated":{"line":10,"column":3},"source":"src/interfaces.ts","original":{"line":9,"column":3}},{"name":"Job","generated":{"line":10,"column":11},"source":"src/interfaces.ts","original":{"line":9,"column":11}},{"generated":{"line":10,"column":17},"source":"src/interfaces.ts","original":{"line":9,"column":17}},{"generated":{"line":10,"column":19},"source":"src/interfaces.ts","original":{"line":9,"column":3}},{"generated":{"line":10,"column":20},"source":"src/interfaces.ts","original":{"line":5,"column":0}},{"name":"exports","generated":{"line":11,"column":0},"source":"src/interfaces.ts","original":{"line":10,"column":0}},{"name":"default","generated":{"line":11,"column":8},"source":"src/interfaces.ts","original":{"line":10,"column":8}},{"generated":{"line":11,"column":15},"source":"src/interfaces.ts","original":{"line":10,"column":0}},{"name":"Job","generated":{"line":11,"column":18},"source":"src/interfaces.ts","original":{"line":10,"column":18}},{"generated":{"line":11,"column":21},"source":"src/interfaces.ts","original":{"line":10,"column":0}},{"generated":{"line":12,"column":0},"source":"src/interfaces.ts","original":{"line":11,"column":0}},{"name":"Type2","generated":{"line":12,"column":4},"source":"src/interfaces.ts","original":{"line":11,"column":4}},{"generated":{"line":12,"column":9},"source":"src/interfaces.ts","original":{"line":11,"column":0}},{"generated":{"line":13,"column":0},"source":"src/interfaces.ts","original":{"line":12,"column":0}},{"generated":{"line":13,"column":1},"source":"src/interfaces.ts","original":{"line":12,"column":1}},{"name":"Type2","generated":{"line":13,"column":11},"source":"src/interfaces.ts","original":{"line":12,"column":11}},{"generated":{"line":13,"column":16},"source":"src/interfaces.ts","original":{"line":12,"column":1}},{"generated":{"line":13,"column":18},"source":"src/interfaces.ts","original":{"line":12,"column":18}},{"name":"Type2","generated":{"line":14,"column":0},"source":"src/interfaces.ts","original":{"line":13,"column":4}},{"generated":{"line":14,"column":10},"source":"src/interfaces.ts","original":{"line":13,"column":10}},{"generated":{"line":14,"column":17},"source":"src/interfaces.ts","original":{"line":13,"column":4}},{"generated":{"line":14,"column":21},"source":"src/interfaces.ts","original":{"line":13,"column":21}},{"generated":{"line":14,"column":28},"source":"src/interfaces.ts","original":{"line":13,"column":4}},{"name":"Type2","generated":{"line":15,"column":0},"source":"src/interfaces.ts","original":{"line":14,"column":4}},{"generated":{"line":15,"column":10},"source":"src/interfaces.ts","original":{"line":14,"column":10}},{"generated":{"line":15,"column":20},"source":"src/interfaces.ts","original":{"line":14,"column":4}},{"generated":{"line":15,"column":24},"source":"src/interfaces.ts","original":{"line":14,"column":24}},{"generated":{"line":15,"column":35},"source":"src/interfaces.ts","original":{"line":14,"column":4}},{"name":"Type2","generated":{"line":16,"column":0},"source":"src/interfaces.ts","original":{"line":15,"column":4}},{"generated":{"line":16,"column":10},"source":"src/interfaces.ts","original":{"line":15,"column":10}},{"generated":{"line":16,"column":16},"source":"src/interfaces.ts","original":{"line":15,"column":4}},{"generated":{"line":16,"column":20},"source":"src/interfaces.ts","original":{"line":15,"column":20}},{"generated":{"line":16,"column":26},"source":"src/interfaces.ts","original":{"line":15,"column":4}},{"generated":{"line":17,"column":0},"source":"src/interfaces.ts","original":{"line":16,"column":1}},{"generated":{"line":17,"column":1},"source":"src/interfaces.ts","original":{"line":12,"column":0}},{"name":"Type2","generated":{"line":17,"column":3},"source":"src/interfaces.ts","original":{"line":16,"column":3}},{"name":"exports","generated":{"line":17,"column":11},"source":"src/interfaces.ts","original":{"line":16,"column":11}},{"name":"Type2","generated":{"line":17,"column":19},"source":"src/interfaces.ts","original":{"line":16,"column":19}},{"generated":{"line":17,"column":24},"source":"src/interfaces.ts","original":{"line":16,"column":11}},{"name":"exports","generated":{"line":17,"column":29},"source":"src/interfaces.ts","original":{"line":16,"column":29}},{"name":"Type2","generated":{"line":17,"column":37},"source":"src/interfaces.ts","original":{"line":16,"column":37}},{"generated":{"line":17,"column":42},"source":"src/interfaces.ts","original":{"line":16,"column":29}},{"generated":{"line":17,"column":45},"source":"src/interfaces.ts","original":{"line":16,"column":45}},{"generated":{"line":17,"column":47},"source":"src/interfaces.ts","original":{"line":16,"column":11}},{"generated":{"line":17,"column":48},"source":"src/interfaces.ts","original":{"line":12,"column":0}}],"sources":{"src/interfaces.ts":"\"use strict\";\nObject.defineProperty(exports, \"__esModule\", { value: true });\nexports.Type2 = void 0;\nvar Job;\n(function (Job) {\n    Job[Job[\"WebDev\"] = 0] = \"WebDev\";\n    Job[Job[\"WebDesigner\"] = 1] = \"WebDesigner\";\n    Job[Job[\"PM\"] = 2] = \"PM\";\n})(Job || (Job = {}));\nexports.default = Job;\nvar Type2;\n(function (Type2) {\n    Type2[\"Video\"] = \"VIDEO\";\n    Type2[\"BlogPost\"] = \"BLOG_POST\";\n    Type2[\"Quiz\"] = \"QUIZ\";\n})(Type2 = exports.Type2 || (exports.Type2 = {}));\n"},"lineCount":null}},"hash":"8546e6875b3a95ce188e1ee110e7a1e4","cacheData":{"env":{}},"id":6}